{
    "check": 1,
    "name": "bihcut",
    "tenses": [
        {
            "name": "present",
            "paradigms": [
                "bizun",
                "bizut",
                "bihcu",
                "bihco",
                "bihcubeahtti",
                "bihcuba",
                "bihcut",
                "bihcubehtet",
                "bihcot"
            ],
            "value": "Present"
        },
        {
            "name": "neg-present",
            "paradigms": [
                "in bizo",
                "it bizo",
                "ii bizo",
                "ean bizo",
                "eahppi bizo",
                "eaba bizo",
                "eat bizo",
                "ehpet bizo",
                "eai bizo"
            ],
            "value": "Neg. Present"
        },
        {
            "name": "preterite",
            "paradigms": [
                "bihcon",
                "bihcot",
                "bizui",
                "bizuime",
                "bizuide",
                "bizuiga",
                "bizuimet",
                "bizuidet",
                "bihco"
            ],
            "value": "Preterite"
        },
        {
            "name": "neg-preterite",
            "paradigms": [
                "in bihcon",
                "it bihcon",
                "ii bihcon",
                "ean bihcon",
                "eahppi bihcon",
                "eaba bihcon",
                "eat bihcon",
                "ehpet bihcon",
                "eai bihcon"
            ],
            "value": "Neg. Preterite"
        },
        {
            "name": "pres-perfect",
            "paradigms": [
                "lean bihcon",
                "leat bihcon",
                "lea bihcon",
                "letne bihcon",
                "leahppi bihcon",
                "leaba bihcon",
                "leat bihcon",
                "lehpet bihcon",
                "leat bihcon"
            ],
            "value": "Present Perfect"
        },
        {
            "name": "past-perfect",
            "paradigms": [
                "ledjen bihcon",
                "ledjet bihcon",
                "lei bihcon",
                "leimme bihcon",
                "leidde bihcon",
                "leigga bihcon",
                "leimmet bihcon",
                "leiddet bihcon",
                "ledje bihcon"
            ],
            "value": "Past Perfect"
        },
        {
            "name": "pres-actioessive",
            "paradigms": [
                "lean bihcume, -min",
                "leat bihcume, -min",
                "lea bihcume, -min",
                "letne bihcume, -min",
                "leahppi bihcume, -min",
                "leaba bihcume, -min",
                "leat bihcume, -min",
                "lehpet bihcume, -min",
                "leat bihcume, -min"
            ],
            "value": "Present Actio Essive"
        },
        {
            "name": "past-actioessive",
            "paradigms": [
                "ledjen bihcume, -min",
                "ledjet bihcume, -min",
                "lei bihcume, -min",
                "leimme bihcume, -min",
                "leidde bihcume, -min",
                "leigga bihcume, -min",
                "leimmet bihcume, -min",
                "leiddet bihcume, -min",
                "ledje bihcume, -min"
            ],
            "value": "Past Actio Essive"
        },
        {
            "name": "conditional",
            "paradigms": [
                "bizošin",
                "bizošit",
                "bizošii",
                "bizošeimme",
                "bizošeidde",
                "bizošeigga",
                "bizošeimmet",
                "bizošeiddet",
                "bizošedje"
            ],
            "value": "Conditional"
        },
        {
            "name": "neg-conditional",
            "paradigms": [
                "in bizoše",
                "it bizoše",
                "ii bizoše",
                "ean bizoše",
                "eahppi bizoše",
                "eaba bizoše",
                "eat bizoše",
                "ehpet bizoše",
                "eai bizoše"
            ],
            "value": "Neg. Conditional"
        },
        {
            "name": "potential",
            "paradigms": [
                "bizožan",
                "bizožat",
                "bizoš",
                "bizožetne",
                "bizožeahppi",
                "bizožeaba",
                "bizožit, -žat",
                "bizožehpet",
                "bizožit"
            ],
            "value": "Potential"
        },
        {
            "name": "neg-potential",
            "paradigms": [
                "in bizoš",
                "it bizoš",
                "ii bizoš",
                "ean bizoš",
                "eahppi bizoš",
                "eaba bizoš",
                "eat bizoš",
                "ehpet bizoš",
                "eai bizoš"
            ],
            "value": "Neg. Potential"
        },
        {
            "name": "imperative",
            "paradigms": [
                "bihcon",
                "bizo",
                "bihcos",
                "bihccu",
                "bihccu",
                "bihcoska",
                "bihcot, bihccot",
                "bihcot, bihccot",
                "bihcoset"
            ],
            "value": "Imperative"
        },
        {
            "name": "neg-imperative",
            "paradigms": [
                "allon bizo",
                "ale bizo",
                "allos bizo",
                "allu bizo",
                "alli bizo",
                "alloska bizo",
                "allot, allut bizo",
                "allet, allit bizo",
                "alloset bizo"
            ],
            "value": "Neg. Imperative"
        }
    ],
    "value": "Bihcut",
    "valid": 1
}