{
    "check": 1,
    "name": "mannat",
    "tenses": [
        {
            "name": "present",
            "paradigms": [
                "manan",
                "manat",
                "manná",
                "manne",
                "mannabeahtti",
                "mannaba",
                "mannat",
                "mannabehtet",
                "mannet"
            ],
            "value": "Present"
        },
        {
            "name": "neg-present",
            "paradigms": [
                "in mana",
                "it mana",
                "ii mana",
                "ean mana",
                "eahppi mana",
                "eaba mana",
                "eat mana",
                "ehpet mana",
                "eai mana"
            ],
            "value": "Neg. Present"
        },
        {
            "name": "preterite",
            "paradigms": [
                "mannen",
                "mannet",
                "manai",
                "manaime",
                "manaide",
                "manaiga",
                "manaimet",
                "manaidet",
                "manne"
            ],
            "value": "Preterite"
        },
        {
            "name": "neg-preterite",
            "paradigms": [
                "in mannan",
                "it mannan",
                "ii mannan",
                "ean mannan",
                "eahppi mannan",
                "eaba mannan",
                "eat mannan",
                "ehpet mannan",
                "eai mannan"
            ],
            "value": "Neg. Preterite"
        },
        {
            "name": "pres-perfect",
            "paradigms": [
                "lean mannan",
                "leat mannan",
                "lea mannan",
                "letne mannan",
                "leahppi mannan",
                "leaba mannan",
                "leat mannan",
                "lehpet mannan",
                "leat mannan"
            ],
            "value": "Present Perfect"
        },
        {
            "name": "past-perfect",
            "paradigms": [
                "ledjen mannan",
                "ledjet mannan",
                "lei mannan",
                "leimme mannan",
                "leidde mannan",
                "leigga mannan",
                "leimmet mannan",
                "leiddet mannan",
                "ledje mannan"
            ],
            "value": "Past Perfect"
        },
        {
            "name": "pres-actioessive",
            "paradigms": [
                "lean manname, -min",
                "leat manname, -min",
                "lea manname, -min",
                "letne manname, -min",
                "leahppi manname, -min",
                "leaba manname, -min",
                "leat manname, -min",
                "lehpet manname, -min",
                "leat manname, -min"
            ],
            "value": "Present Actio Essive"
        },
        {
            "name": "past-actioessive",
            "paradigms": [
                "ledjen manname, -min",
                "ledjet manname, -min",
                "lei manname, -min",
                "leimme manname, -min",
                "leidde manname, -min",
                "leigga manname, -min",
                "leimmet manname, -min",
                "leiddet manname, -min",
                "ledje manname, -min"
            ],
            "value": "Past Actio Essive"
        },
        {
            "name": "conditional",
            "paradigms": [
                "manašin",
                "manašit",
                "manašii",
                "manašeimme",
                "manašeidde",
                "manašeigga",
                "manašeimmet",
                "manašeiddet",
                "manašedje"
            ],
            "value": "Conditional"
        },
        {
            "name": "neg-conditional",
            "paradigms": [
                "in manaše",
                "it manaše",
                "ii manaše",
                "ean manaše",
                "eahppi manaše",
                "eaba manaše",
                "eat manaše",
                "ehpet manaše",
                "eai manaše"
            ],
            "value": "Neg. Conditional"
        },
        {
            "name": "potential",
            "paradigms": [
                "manažan",
                "manažat",
                "manaš",
                "manažetne",
                "manažeahppi",
                "manažeaba",
                "manažit, -žat",
                "manažehpet",
                "manažit"
            ],
            "value": "Potential"
        },
        {
            "name": "neg-potential",
            "paradigms": [
                "in manaš",
                "it manaš",
                "ii manaš",
                "ean manaš",
                "eahppi manaš",
                "eaba manaš",
                "eat manaš",
                "ehpet manaš",
                "eai manaš"
            ],
            "value": "Neg. Potential"
        },
        {
            "name": "imperative",
            "paradigms": [
                "mannon",
                "mana",
                "mannos",
                "mannu",
                "manni",
                "mannoska",
                "mannot",
                "mannet, mannit",
                "mannoset"
            ],
            "value": "Imperative"
        },
        {
            "name": "neg-imperative",
            "paradigms": [
                "allon mana",
                "ale mana",
                "allos mana",
                "allu mana",
                "alli mana",
                "alloska mana",
                "allot, allut mana",
                "allet, allit mana",
                "alloset mana"
            ],
            "value": "Neg. Imperative"
        }
    ],
    "value": "Mannat",
    "valid": 1
}