{
    "check": 1,
    "name": "nollagit",
    "tenses": [
        {
            "name": "present",
            "paradigms": [
                "nollagan",
                "nollagat",
                "nollaga",
                "nollagetne",
                "nollageahppi",
                "nollageaba",
                "nollagit, -gat",
                "nollagehpet",
                "nollagit"
            ],
            "value": "Present"
        },
        {
            "name": "neg-present",
            "paradigms": [
                "in nollat",
                "it nollat",
                "ii nollat",
                "ean nollat",
                "eahppi nollat",
                "eaba nollat",
                "eat nollat",
                "ehpet nollat",
                "eai nollat"
            ],
            "value": "Neg. Present"
        },
        {
            "name": "preterite",
            "paradigms": [
                "nollagin",
                "nollagit",
                "nollagii",
                "nollageimme",
                "nollageidde",
                "nollageigga",
                "nollageimmet",
                "nollageiddet",
                "nollagedje"
            ],
            "value": "Preterite"
        },
        {
            "name": "neg-preterite",
            "paradigms": [
                "in nollagan",
                "it nollagan",
                "ii nollagan",
                "ean nollagan",
                "eahppi nollagan",
                "eaba nollagan",
                "eat nollagan",
                "ehpet nollagan",
                "eai nollagan"
            ],
            "value": "Neg. Preterite"
        },
        {
            "name": "pres-perfect",
            "paradigms": [
                "lean nollagan",
                "leat nollagan",
                "lea nollagan",
                "letne nollagan",
                "leahppi nollagan",
                "leaba nollagan",
                "leat nollagan",
                "lehpet nollagan",
                "leat nollagan"
            ],
            "value": "Present Perfect"
        },
        {
            "name": "past-perfect",
            "paradigms": [
                "ledjen nollagan",
                "ledjet nollagan",
                "lei nollagan",
                "leimme nollagan",
                "leidde nollagan",
                "leigga nollagan",
                "leimmet nollagan",
                "leiddet nollagan",
                "ledje nollagan"
            ],
            "value": "Past Perfect"
        },
        {
            "name": "pres-actioessive",
            "paradigms": [
                "lean nollageame, -men",
                "leat nollageame, -men",
                "lea nollageame, -men",
                "letne nollageame, -men",
                "leahppi nollageame, -men",
                "leaba nollageame, -men",
                "leat nollageame, -men",
                "lehpet nollageame, -men",
                "leat nollageame, -men"
            ],
            "value": "Present Actio Essive"
        },
        {
            "name": "past-actioessive",
            "paradigms": [
                "ledjen nollageame, -men",
                "ledjet nollageame, -men",
                "lei nollageame, -men",
                "leimme nollageame, -men",
                "leidde nollageame, -men",
                "leigga nollageame, -men",
                "leimmet nollageame, -men",
                "leiddet nollageame, -men",
                "ledje nollageame, -men"
            ],
            "value": "Past Actio Essive"
        },
        {
            "name": "conditional",
            "paradigms": [
                "nollagivččen",
                "nollagivččet",
                "nollagivččii",
                "nollagivččiime",
                "nollagivččiide",
                "nollagivččiiga",
                "nollagivččiimet",
                "nollagivččiidet",
                "nollagivčče"
            ],
            "value": "Conditional"
        },
        {
            "name": "neg-conditional",
            "paradigms": [
                "in nollagivčče",
                "it nollagivčče",
                "ii nollagivčče",
                "ean nollagivčče",
                "eahppi nollagivčče",
                "eaba nollagivčče",
                "eat nollagivčče",
                "ehpet nollagivčče",
                "eai nollagivčče"
            ],
            "value": "Neg. Conditional"
        },
        {
            "name": "potential",
            "paradigms": [
                "nollageaččan",
                "nollageaččat",
                "nollageaš, -geš, -geažžá",
                "nollagežže",
                "nollageažžabeahtti",
                "nollageažžaba",
                "nollageažžat",
                "nollageažžabehtet",
                "nollagežžet"
            ],
            "value": "Potential"
        },
        {
            "name": "neg-potential",
            "paradigms": [
                "in nollageaš, -geš, -geažžá",
                "it nollageaš, -geš, -geažžá",
                "ii nollageaš, -geš, -geažžá",
                "ean nollageaš, -geš, -geažžá",
                "eahppi nollageaš, -geš, -geažžá",
                "eaba nollageaš, -geš, -geažžá",
                "eat nollageaš, -geš, -geažžá",
                "ehpet nollageaš, -geš, -geažžá",
                "eai nollageaš, -geš, -geažžá"
            ],
            "value": "Neg. Potential"
        },
        {
            "name": "imperative",
            "paradigms": [
                "nollagehkon",
                "nollat",
                "nollagehkos, nollagus",
                "nollageadnu",
                "nollageahkki",
                "nollagehkoska",
                "nollagehkot, nollageahkkut, nollagetnot, nollageadnot",
                "nollagehket",
                "nollagehkoset"
            ],
            "value": "Imperative"
        },
        {
            "name": "neg-imperative",
            "paradigms": [
                "allon nollat",
                "ale nollat",
                "allos nollat",
                "allu nollat",
                "alli nollat",
                "alloska nollat",
                "allot, allut nollat",
                "allet, allit nollat",
                "alloset nollat"
            ],
            "value": "Neg. Imperative"
        }
    ],
    "value": "Nollagit",
    "valid": 1
}