{
    "check": 1,
    "name": "juollut",
    "tenses": [
        {
            "name": "present",
            "paradigms": [
                "juolun",
                "juolut",
                "juollu",
                "jullo",
                "juollubeahtti",
                "juolluba",
                "juollut",
                "juollubehtet",
                "jullot"
            ],
            "value": "Present"
        },
        {
            "name": "neg-present",
            "paradigms": [
                "in juolo",
                "it juolo",
                "ii juolo",
                "ean juolo",
                "eahppi juolo",
                "eaba juolo",
                "eat juolo",
                "ehpet juolo",
                "eai juolo"
            ],
            "value": "Neg. Present"
        },
        {
            "name": "preterite",
            "paradigms": [
                "jullon",
                "jullot",
                "juolui",
                "juoluime",
                "juoluide",
                "juoluiga",
                "juoluimet",
                "juoluidet",
                "jullo"
            ],
            "value": "Preterite"
        },
        {
            "name": "neg-preterite",
            "paradigms": [
                "in jullon",
                "it jullon",
                "ii jullon",
                "ean jullon",
                "eahppi jullon",
                "eaba jullon",
                "eat jullon",
                "ehpet jullon",
                "eai jullon"
            ],
            "value": "Neg. Preterite"
        },
        {
            "name": "pres-perfect",
            "paradigms": [
                "lean jullon",
                "leat jullon",
                "lea jullon",
                "letne jullon",
                "leahppi jullon",
                "leaba jullon",
                "leat jullon",
                "lehpet jullon",
                "leat jullon"
            ],
            "value": "Present Perfect"
        },
        {
            "name": "past-perfect",
            "paradigms": [
                "ledjen jullon",
                "ledjet jullon",
                "lei jullon",
                "leimme jullon",
                "leidde jullon",
                "leigga jullon",
                "leimmet jullon",
                "leiddet jullon",
                "ledje jullon"
            ],
            "value": "Past Perfect"
        },
        {
            "name": "pres-actioessive",
            "paradigms": [
                "lean juollume, -min",
                "leat juollume, -min",
                "lea juollume, -min",
                "letne juollume, -min",
                "leahppi juollume, -min",
                "leaba juollume, -min",
                "leat juollume, -min",
                "lehpet juollume, -min",
                "leat juollume, -min"
            ],
            "value": "Present Actio Essive"
        },
        {
            "name": "past-actioessive",
            "paradigms": [
                "ledjen juollume, -min",
                "ledjet juollume, -min",
                "lei juollume, -min",
                "leimme juollume, -min",
                "leidde juollume, -min",
                "leigga juollume, -min",
                "leimmet juollume, -min",
                "leiddet juollume, -min",
                "ledje juollume, -min"
            ],
            "value": "Past Actio Essive"
        },
        {
            "name": "conditional",
            "paradigms": [
                "julošin",
                "julošit",
                "julošii",
                "julošeimme",
                "julošeidde",
                "julošeigga",
                "julošeimmet",
                "julošeiddet",
                "julošedje"
            ],
            "value": "Conditional"
        },
        {
            "name": "neg-conditional",
            "paradigms": [
                "in juloše",
                "it juloše",
                "ii juloše",
                "ean juloše",
                "eahppi juloše",
                "eaba juloše",
                "eat juloše",
                "ehpet juloše",
                "eai juloše"
            ],
            "value": "Neg. Conditional"
        },
        {
            "name": "potential",
            "paradigms": [
                "juložan",
                "juložat",
                "juloš",
                "juložetne",
                "juložeahppi",
                "juložeaba",
                "juložit, -žat",
                "juložehpet",
                "juložit"
            ],
            "value": "Potential"
        },
        {
            "name": "neg-potential",
            "paradigms": [
                "in juloš",
                "it juloš",
                "ii juloš",
                "ean juloš",
                "eahppi juloš",
                "eaba juloš",
                "eat juloš",
                "ehpet juloš",
                "eai juloš"
            ],
            "value": "Neg. Potential"
        },
        {
            "name": "imperative",
            "paradigms": [
                "jullon",
                "juolo",
                "jullos",
                "juollu",
                "juollu",
                "julloska",
                "jullot, juollot",
                "jullot, juollot",
                "julloset"
            ],
            "value": "Imperative"
        },
        {
            "name": "neg-imperative",
            "paradigms": [
                "allon juolo",
                "ale juolo",
                "allos juolo",
                "allu juolo",
                "alli juolo",
                "alloska juolo",
                "allot, allut juolo",
                "allet, allit juolo",
                "alloset juolo"
            ],
            "value": "Neg. Imperative"
        }
    ],
    "value": "Juollut",
    "valid": 1
}