{
    "check": 1,
    "name": "millet",
    "tenses": [
        {
            "name": "present",
            "paradigms": [
                "millen",
                "millet",
                "mille",
                "millejetne",
                "millebeahtti",
                "milleba",
                "millet",
                "millebehtet",
                "millejit"
            ],
            "value": "Present"
        },
        {
            "name": "neg-present",
            "paradigms": [
                "in mille",
                "it mille",
                "ii mille",
                "ean mille",
                "eahppi mille",
                "eaba mille",
                "eat mille",
                "ehpet mille",
                "eai mille"
            ],
            "value": "Neg. Present"
        },
        {
            "name": "preterite",
            "paradigms": [
                "millejin",
                "millejit",
                "millii",
                "milliime",
                "milliide",
                "milliiga",
                "milliimet",
                "milliidet",
                "millejedje"
            ],
            "value": "Preterite"
        },
        {
            "name": "neg-preterite",
            "paradigms": [
                "in millen",
                "it millen",
                "ii millen",
                "ean millen",
                "eahppi millen",
                "eaba millen",
                "eat millen",
                "ehpet millen",
                "eai millen"
            ],
            "value": "Neg. Preterite"
        },
        {
            "name": "pres-perfect",
            "paradigms": [
                "lean millen",
                "leat millen",
                "lea millen",
                "letne millen",
                "leahppi millen",
                "leaba millen",
                "leat millen",
                "lehpet millen",
                "leat millen"
            ],
            "value": "Present Perfect"
        },
        {
            "name": "past-perfect",
            "paradigms": [
                "ledjen millen",
                "ledjet millen",
                "lei millen",
                "leimme millen",
                "leidde millen",
                "leigga millen",
                "leimmet millen",
                "leiddet millen",
                "ledje millen"
            ],
            "value": "Past Perfect"
        },
        {
            "name": "pres-actioessive",
            "paradigms": [
                "lean milleme, -min",
                "leat milleme, -min",
                "lea milleme, -min",
                "letne milleme, -min",
                "leahppi milleme, -min",
                "leaba milleme, -min",
                "leat milleme, -min",
                "lehpet milleme, -min",
                "leat milleme, -min"
            ],
            "value": "Present Actio Essive"
        },
        {
            "name": "past-actioessive",
            "paradigms": [
                "ledjen milleme, -min",
                "ledjet milleme, -min",
                "lei milleme, -min",
                "leimme milleme, -min",
                "leidde milleme, -min",
                "leigga milleme, -min",
                "leimmet milleme, -min",
                "leiddet milleme, -min",
                "ledje milleme, -min"
            ],
            "value": "Past Actio Essive"
        },
        {
            "name": "conditional",
            "paradigms": [
                "millešin",
                "millešit",
                "millešii",
                "millešeimme",
                "millešeidde",
                "millešeigga",
                "millešeimmet",
                "millešeiddet",
                "millešedje"
            ],
            "value": "Conditional"
        },
        {
            "name": "neg-conditional",
            "paradigms": [
                "in milleše",
                "it milleše",
                "ii milleše",
                "ean milleše",
                "eahppi milleše",
                "eaba milleše",
                "eat milleše",
                "ehpet milleše",
                "eai milleše"
            ],
            "value": "Neg. Conditional"
        },
        {
            "name": "potential",
            "paradigms": [
                "milležan",
                "milležat",
                "milleš",
                "milležetne",
                "milležeahppi",
                "milležeaba",
                "milležit, -žat",
                "milležehpet",
                "milležit"
            ],
            "value": "Potential"
        },
        {
            "name": "neg-potential",
            "paradigms": [
                "in milleš",
                "it milleš",
                "ii milleš",
                "ean milleš",
                "eahppi milleš",
                "eaba milleš",
                "eat milleš",
                "ehpet milleš",
                "eai milleš"
            ],
            "value": "Neg. Potential"
        },
        {
            "name": "imperative",
            "paradigms": [
                "millejehkon",
                "mille",
                "millejehkos",
                "millejeadnu",
                "millejeahkki",
                "millejehkoska",
                "millejeahkkut, millejeadnot, millejehkot, millejetnot",
                "millejeahkkit",
                "millejehkoset"
            ],
            "value": "Imperative"
        },
        {
            "name": "neg-imperative",
            "paradigms": [
                "allon mille",
                "ale mille",
                "allos mille",
                "allu mille",
                "alli mille",
                "alloska mille",
                "allot, allut mille",
                "allet, allit mille",
                "alloset mille"
            ],
            "value": "Neg. Imperative"
        }
    ],
    "value": "Millet",
    "valid": 1
}