{
    "check": 1,
    "name": "ravgat",
    "tenses": [
        {
            "name": "present",
            "paradigms": [
                "ravggan",
                "ravggat",
                "ravgá",
                "ravge",
                "ravgabeahtti",
                "ravgaba",
                "ravgat",
                "ravgabehtet",
                "ravget"
            ],
            "value": "Present"
        },
        {
            "name": "neg-present",
            "paradigms": [
                "in ravgga",
                "it ravgga",
                "ii ravgga",
                "ean ravgga",
                "eahppi ravgga",
                "eaba ravgga",
                "eat ravgga",
                "ehpet ravgga",
                "eai ravgga"
            ],
            "value": "Neg. Present"
        },
        {
            "name": "preterite",
            "paradigms": [
                "ravgen",
                "ravget",
                "ravggai",
                "ravggaime",
                "ravggaide",
                "ravggaiga",
                "ravggaimet",
                "ravggaidet",
                "ravge"
            ],
            "value": "Preterite"
        },
        {
            "name": "neg-preterite",
            "paradigms": [
                "in ravgan",
                "it ravgan",
                "ii ravgan",
                "ean ravgan",
                "eahppi ravgan",
                "eaba ravgan",
                "eat ravgan",
                "ehpet ravgan",
                "eai ravgan"
            ],
            "value": "Neg. Preterite"
        },
        {
            "name": "pres-perfect",
            "paradigms": [
                "lean ravgan",
                "leat ravgan",
                "lea ravgan",
                "letne ravgan",
                "leahppi ravgan",
                "leaba ravgan",
                "leat ravgan",
                "lehpet ravgan",
                "leat ravgan"
            ],
            "value": "Present Perfect"
        },
        {
            "name": "past-perfect",
            "paradigms": [
                "ledjen ravgan",
                "ledjet ravgan",
                "lei ravgan",
                "leimme ravgan",
                "leidde ravgan",
                "leigga ravgan",
                "leimmet ravgan",
                "leiddet ravgan",
                "ledje ravgan"
            ],
            "value": "Past Perfect"
        },
        {
            "name": "pres-actioessive",
            "paradigms": [
                "lean ravgame, -min",
                "leat ravgame, -min",
                "lea ravgame, -min",
                "letne ravgame, -min",
                "leahppi ravgame, -min",
                "leaba ravgame, -min",
                "leat ravgame, -min",
                "lehpet ravgame, -min",
                "leat ravgame, -min"
            ],
            "value": "Present Actio Essive"
        },
        {
            "name": "past-actioessive",
            "paradigms": [
                "ledjen ravgame, -min",
                "ledjet ravgame, -min",
                "lei ravgame, -min",
                "leimme ravgame, -min",
                "leidde ravgame, -min",
                "leigga ravgame, -min",
                "leimmet ravgame, -min",
                "leiddet ravgame, -min",
                "ledje ravgame, -min"
            ],
            "value": "Past Actio Essive"
        },
        {
            "name": "conditional",
            "paradigms": [
                "ravggašin",
                "ravggašit",
                "ravggašii",
                "ravggašeimme",
                "ravggašeidde",
                "ravggašeigga",
                "ravggašeimmet",
                "ravggašeiddet",
                "ravggašedje"
            ],
            "value": "Conditional"
        },
        {
            "name": "neg-conditional",
            "paradigms": [
                "in ravggaše",
                "it ravggaše",
                "ii ravggaše",
                "ean ravggaše",
                "eahppi ravggaše",
                "eaba ravggaše",
                "eat ravggaše",
                "ehpet ravggaše",
                "eai ravggaše"
            ],
            "value": "Neg. Conditional"
        },
        {
            "name": "potential",
            "paradigms": [
                "ravggažan",
                "ravggažat",
                "ravggaš",
                "ravggažetne",
                "ravggažeahppi",
                "ravggažeaba",
                "ravggažit, -žat",
                "ravggažehpet",
                "ravggažit"
            ],
            "value": "Potential"
        },
        {
            "name": "neg-potential",
            "paradigms": [
                "in ravggaš",
                "it ravggaš",
                "ii ravggaš",
                "ean ravggaš",
                "eahppi ravggaš",
                "eaba ravggaš",
                "eat ravggaš",
                "ehpet ravggaš",
                "eai ravggaš"
            ],
            "value": "Neg. Potential"
        },
        {
            "name": "imperative",
            "paradigms": [
                "ravgon",
                "ravgga",
                "ravgos",
                "ravgu",
                "ravgi",
                "ravgoska",
                "ravgot",
                "ravget, ravgit",
                "ravgoset"
            ],
            "value": "Imperative"
        },
        {
            "name": "neg-imperative",
            "paradigms": [
                "allon ravgga",
                "ale ravgga",
                "allos ravgga",
                "allu ravgga",
                "alli ravgga",
                "alloska ravgga",
                "allot, allut ravgga",
                "allet, allit ravgga",
                "alloset ravgga"
            ],
            "value": "Neg. Imperative"
        }
    ],
    "value": "Ravgat",
    "valid": 1
}