{
    "check": 1,
    "name": "čierastit",
    "tenses": [
        {
            "name": "present",
            "paradigms": [
                "čierastan",
                "čierastat",
                "čierasta",
                "čierastetne",
                "čierasteahppi",
                "čierasteaba",
                "čierastit, -tat",
                "čierastehpet",
                "čierastit"
            ],
            "value": "Present"
        },
        {
            "name": "neg-present",
            "paradigms": [
                "in čieras",
                "it čieras",
                "ii čieras",
                "ean čieras",
                "eahppi čieras",
                "eaba čieras",
                "eat čieras",
                "ehpet čieras",
                "eai čieras"
            ],
            "value": "Neg. Present"
        },
        {
            "name": "preterite",
            "paradigms": [
                "čierastin",
                "čierastit",
                "čierastii",
                "čierasteimme",
                "čierasteidde",
                "čierasteigga",
                "čierasteimmet",
                "čierasteiddet",
                "čierastedje"
            ],
            "value": "Preterite"
        },
        {
            "name": "neg-preterite",
            "paradigms": [
                "in čierastan",
                "it čierastan",
                "ii čierastan",
                "ean čierastan",
                "eahppi čierastan",
                "eaba čierastan",
                "eat čierastan",
                "ehpet čierastan",
                "eai čierastan"
            ],
            "value": "Neg. Preterite"
        },
        {
            "name": "pres-perfect",
            "paradigms": [
                "lean čierastan",
                "leat čierastan",
                "lea čierastan",
                "letne čierastan",
                "leahppi čierastan",
                "leaba čierastan",
                "leat čierastan",
                "lehpet čierastan",
                "leat čierastan"
            ],
            "value": "Present Perfect"
        },
        {
            "name": "past-perfect",
            "paradigms": [
                "ledjen čierastan",
                "ledjet čierastan",
                "lei čierastan",
                "leimme čierastan",
                "leidde čierastan",
                "leigga čierastan",
                "leimmet čierastan",
                "leiddet čierastan",
                "ledje čierastan"
            ],
            "value": "Past Perfect"
        },
        {
            "name": "pres-actioessive",
            "paradigms": [
                "lean čierasteame, -men",
                "leat čierasteame, -men",
                "lea čierasteame, -men",
                "letne čierasteame, -men",
                "leahppi čierasteame, -men",
                "leaba čierasteame, -men",
                "leat čierasteame, -men",
                "lehpet čierasteame, -men",
                "leat čierasteame, -men"
            ],
            "value": "Present Actio Essive"
        },
        {
            "name": "past-actioessive",
            "paradigms": [
                "ledjen čierasteame, -men",
                "ledjet čierasteame, -men",
                "lei čierasteame, -men",
                "leimme čierasteame, -men",
                "leidde čierasteame, -men",
                "leigga čierasteame, -men",
                "leimmet čierasteame, -men",
                "leiddet čierasteame, -men",
                "ledje čierasteame, -men"
            ],
            "value": "Past Actio Essive"
        },
        {
            "name": "conditional",
            "paradigms": [
                "čierastivččen",
                "čierastivččet",
                "čierastivččii",
                "čierastivččiime",
                "čierastivččiide",
                "čierastivččiiga",
                "čierastivččiimet",
                "čierastivččiidet",
                "čierastivčče"
            ],
            "value": "Conditional"
        },
        {
            "name": "neg-conditional",
            "paradigms": [
                "in čierastivčče",
                "it čierastivčče",
                "ii čierastivčče",
                "ean čierastivčče",
                "eahppi čierastivčče",
                "eaba čierastivčče",
                "eat čierastivčče",
                "ehpet čierastivčče",
                "eai čierastivčče"
            ],
            "value": "Neg. Conditional"
        },
        {
            "name": "potential",
            "paradigms": [
                "čierasteaččan",
                "čierasteaččat",
                "čierasteaš, -teš, -teažžá",
                "čierastežže",
                "čierasteažžabeahtti",
                "čierasteažžaba",
                "čierasteažžat",
                "čierasteažžabehtet",
                "čierastežžet"
            ],
            "value": "Potential"
        },
        {
            "name": "neg-potential",
            "paradigms": [
                "in čierasteaš, -teš, -teažžá",
                "it čierasteaš, -teš, -teažžá",
                "ii čierasteaš, -teš, -teažžá",
                "ean čierasteaš, -teš, -teažžá",
                "eahppi čierasteaš, -teš, -teažžá",
                "eaba čierasteaš, -teš, -teažžá",
                "eat čierasteaš, -teš, -teažžá",
                "ehpet čierasteaš, -teš, -teažžá",
                "eai čierasteaš, -teš, -teažžá"
            ],
            "value": "Neg. Potential"
        },
        {
            "name": "imperative",
            "paradigms": [
                "čierastehkon",
                "čieras",
                "čierastehkos, čierastus",
                "čierasteadnu",
                "čierasteahkki",
                "čierastehkoska",
                "čierastehkot, čierasteahkkut, čierastetnot, čierasteadnot",
                "čierastehket",
                "čierastehkoset"
            ],
            "value": "Imperative"
        },
        {
            "name": "neg-imperative",
            "paradigms": [
                "allon čieras",
                "ale čieras",
                "allos čieras",
                "allu čieras",
                "alli čieras",
                "alloska čieras",
                "allot, allut čieras",
                "allet, allit čieras",
                "alloset čieras"
            ],
            "value": "Neg. Imperative"
        }
    ],
    "value": "Čierastit",
    "valid": 1
}