{
    "check": 1,
    "name": "čohkkát",
    "tenses": [
        {
            "name": "present",
            "paradigms": [
                "čohkkán",
                "čohkkát",
                "čohkká",
                "čohkkájetne",
                "čohkkábeahtti",
                "čohkkába",
                "čohkkát",
                "čohkkábehtet",
                "čohkkájit"
            ],
            "value": "Present"
        },
        {
            "name": "neg-present",
            "paradigms": [
                "in čohkká",
                "it čohkká",
                "ii čohkká",
                "ean čohkká",
                "eahppi čohkká",
                "eaba čohkká",
                "eat čohkká",
                "ehpet čohkká",
                "eai čohkká"
            ],
            "value": "Neg. Present"
        },
        {
            "name": "preterite",
            "paradigms": [
                "čohkkájin",
                "čohkkájit",
                "čohkkái",
                "čohkkáime",
                "čohkkáide",
                "čohkkáiga",
                "čohkkáimet",
                "čohkkáidet",
                "čohkkájedje"
            ],
            "value": "Preterite"
        },
        {
            "name": "neg-preterite",
            "paradigms": [
                "in čohkkán",
                "it čohkkán",
                "ii čohkkán",
                "ean čohkkán",
                "eahppi čohkkán",
                "eaba čohkkán",
                "eat čohkkán",
                "ehpet čohkkán",
                "eai čohkkán"
            ],
            "value": "Neg. Preterite"
        },
        {
            "name": "pres-perfect",
            "paradigms": [
                "lean čohkkán",
                "leat čohkkán",
                "lea čohkkán",
                "letne čohkkán",
                "leahppi čohkkán",
                "leaba čohkkán",
                "leat čohkkán",
                "lehpet čohkkán",
                "leat čohkkán"
            ],
            "value": "Present Perfect"
        },
        {
            "name": "past-perfect",
            "paradigms": [
                "ledjen čohkkán",
                "ledjet čohkkán",
                "lei čohkkán",
                "leimme čohkkán",
                "leidde čohkkán",
                "leigga čohkkán",
                "leimmet čohkkán",
                "leiddet čohkkán",
                "ledje čohkkán"
            ],
            "value": "Past Perfect"
        },
        {
            "name": "pres-actioessive",
            "paradigms": [
                "lean čohkkáme, -min",
                "leat čohkkáme, -min",
                "lea čohkkáme, -min",
                "letne čohkkáme, -min",
                "leahppi čohkkáme, -min",
                "leaba čohkkáme, -min",
                "leat čohkkáme, -min",
                "lehpet čohkkáme, -min",
                "leat čohkkáme, -min"
            ],
            "value": "Present Actio Essive"
        },
        {
            "name": "past-actioessive",
            "paradigms": [
                "ledjen čohkkáme, -min",
                "ledjet čohkkáme, -min",
                "lei čohkkáme, -min",
                "leimme čohkkáme, -min",
                "leidde čohkkáme, -min",
                "leigga čohkkáme, -min",
                "leimmet čohkkáme, -min",
                "leiddet čohkkáme, -min",
                "ledje čohkkáme, -min"
            ],
            "value": "Past Actio Essive"
        },
        {
            "name": "conditional",
            "paradigms": [
                "čohkkášin",
                "čohkkášit",
                "čohkkášii",
                "čohkkášeimme",
                "čohkkášeidde",
                "čohkkášeigga",
                "čohkkášeimmet",
                "čohkkášeiddet",
                "čohkkášedje"
            ],
            "value": "Conditional"
        },
        {
            "name": "neg-conditional",
            "paradigms": [
                "in čohkkáše",
                "it čohkkáše",
                "ii čohkkáše",
                "ean čohkkáše",
                "eahppi čohkkáše",
                "eaba čohkkáše",
                "eat čohkkáše",
                "ehpet čohkkáše",
                "eai čohkkáše"
            ],
            "value": "Neg. Conditional"
        },
        {
            "name": "potential",
            "paradigms": [
                "čohkkážan",
                "čohkkážat",
                "čohkkáš",
                "čohkkážetne",
                "čohkkážeahppi",
                "čohkkážeaba",
                "čohkkážit, -žat",
                "čohkkážehpet",
                "čohkkážit"
            ],
            "value": "Potential"
        },
        {
            "name": "neg-potential",
            "paradigms": [
                "in čohkkáš",
                "it čohkkáš",
                "ii čohkkáš",
                "ean čohkkáš",
                "eahppi čohkkáš",
                "eaba čohkkáš",
                "eat čohkkáš",
                "ehpet čohkkáš",
                "eai čohkkáš"
            ],
            "value": "Neg. Potential"
        },
        {
            "name": "imperative",
            "paradigms": [
                "čohkkájehkon",
                "čohkká",
                "čohkkájehkos",
                "čohkkájeadnu",
                "čohkkájeahkki",
                "čohkkájehkoska",
                "čohkkájeahkkut, čohkkájeadnot, čohkkájehkot, čohkkájetnot",
                "čohkkájeahkkit",
                "čohkkájehkoset"
            ],
            "value": "Imperative"
        },
        {
            "name": "neg-imperative",
            "paradigms": [
                "allon čohkká",
                "ale čohkká",
                "allos čohkká",
                "allu čohkká",
                "alli čohkká",
                "alloska čohkká",
                "allot, allut čohkká",
                "allet, allit čohkká",
                "alloset čohkká"
            ],
            "value": "Neg. Imperative"
        }
    ],
    "value": "Čohkkát",
    "valid": 1
}